{
  "summary": {
    "feature_count": 110,
    "avg_missing_rate": 0.009910201814478803,
    "avg_drift_score": Infinity,
    "avg_abs_ic20": 0.12808588135714088,
    "avg_abs_ic60": NaN
  },
  "top_stable_features": [
    {
      "feature": "volatility_5d",
      "missing_rate": 0.0,
      "drift_score": 0.0157585659308605,
      "ic_20d": -0.34615686569994797,
      "ic_60d": NaN,
      "stability_score": 0.7059232256432145
    },
    {
      "feature": "intraday_range_ma",
      "missing_rate": 0.0,
      "drift_score": 0.02024646088792424,
      "ic_20d": -0.29308882081261955,
      "ic_60d": NaN,
      "stability_score": 0.69533714071534
    },
    {
      "feature": "volatility_60d",
      "missing_rate": 0.0006788866259334691,
      "drift_score": 0.030402138015171623,
      "ic_20d": -0.2916400702883236,
      "ic_60d": NaN,
      "stability_score": 0.6919478661896159
    },
    {
      "feature": "volatility_20d",
      "missing_rate": 0.0,
      "drift_score": 0.023535286779263163,
      "ic_20d": -0.27794679174992537,
      "ic_60d": NaN,
      "stability_score": 0.6917424544406391
    },
    {
      "feature": "atr_14_pct",
      "missing_rate": 0.0,
      "drift_score": 0.007819265296148802,
      "ic_20d": -0.24314557030357997,
      "ic_60d": NaN,
      "stability_score": 0.6902228951768774
    },
    {
      "feature": "intraday_range",
      "missing_rate": 0.0,
      "drift_score": 0.03059675194737324,
      "ic_20d": -0.26601731588271266,
      "ic_60d": NaN,
      "stability_score": 0.6876465151300064
    },
    {
      "feature": "lower_shadow_pct",
      "missing_rate": 0.0,
      "drift_score": 0.02649179937270023,
      "ic_20d": -0.2504256875762574,
      "ic_60d": NaN,
      "stability_score": 0.6860820663881109
    },
    {
      "feature": "atr_14",
      "missing_rate": 0.0,
      "drift_score": 0.10190136104656462,
      "ic_20d": -0.3312502096144619,
      "ic_60d": NaN,
      "stability_score": 0.6802254610141295
    },
    {
      "feature": "macd",
      "missing_rate": 0.0,
      "drift_score": 0.09676021935909031,
      "ic_20d": 0.29246600031870507,
      "ic_60d": NaN,
      "stability_score": 0.6747144469503287
    },
    {
      "feature": "is_doji",
      "missing_rate": 0.0,
      "drift_score": 0.0421361807346305,
      "ic_20d": 0.2066209168438069,
      "ic_60d": NaN,
      "stability_score": 0.6740289076820745
    },
    {
      "feature": "near_low_60",
      "missing_rate": 0.0,
      "drift_score": 0.03729150341102557,
      "ic_20d": 0.19824830342051206,
      "ic_60d": NaN,
      "stability_score": 0.6739082003644075
    },
    {
      "feature": "macd_signal",
      "missing_rate": 0.0,
      "drift_score": 0.09109179592762713,
      "ic_20d": 0.26120924747894914,
      "ic_60d": NaN,
      "stability_score": 0.6706655691310246
    },
    {
      "feature": "near_low_20",
      "missing_rate": 0.0,
      "drift_score": 0.06055622213700951,
      "ic_20d": 0.21175572946185459,
      "ic_60d": NaN,
      "stability_score": 0.6699276877521396
    },
    {
      "feature": "return_5d",
      "missing_rate": 0.0,
      "drift_score": 0.019453272592210608,
      "ic_20d": 0.14186448365234874,
      "ic_60d": NaN,
      "stability_score": 0.6691016654392797
    },
    {
      "feature": "upper_shadow_pct",
      "missing_rate": 0.0,
      "drift_score": 0.00972952114552514,
      "ic_20d": -0.12526803527749136,
      "ic_60d": NaN,
      "stability_score": 0.6690311752574774
    },
    {
      "feature": "bb_breakout_lower",
      "missing_rate": 0.0,
      "drift_score": 0.014774578095649938,
      "ic_20d": -0.12783683739634474,
      "ic_60d": NaN,
      "stability_score": 0.6680036061151953
    },
    {
      "feature": "fund_market_cap",
      "missing_rate": 0.0,
      "drift_score": 0.02803185326617843,
      "ic_20d": -0.1370914913267258,
      "ic_60d": NaN,
      "stability_score": 0.665810762526708
    },
    {
      "feature": "bb_upper",
      "missing_rate": 0.0,
      "drift_score": 0.1017161852112977,
      "ic_20d": -0.24567215575141504,
      "ic_60d": NaN,
      "stability_score": 0.6652950623364208
    },
    {
      "feature": "ma_60",
      "missing_rate": 0.0005091649694501018,
      "drift_score": 0.10166157697927775,
      "ic_20d": -0.24170968715879632,
      "ic_60d": NaN,
      "stability_score": 0.6644369203452238
    },
    {
      "feature": "ema_26",
      "missing_rate": 0.0,
      "drift_score": 0.10168914460979094,
      "ic_20d": -0.2350456761366642,
      "ic_60d": NaN,
      "stability_score": 0.6634421119784868
    },
    {
      "feature": "bb_middle",
      "missing_rate": 0.0,
      "drift_score": 0.10171544875748954,
      "ic_20d": -0.2334276339508976,
      "ic_60d": NaN,
      "stability_score": 0.6631524530448877
    },
    {
      "feature": "ma_20",
      "missing_rate": 0.0,
      "drift_score": 0.10171544875748954,
      "ic_20d": -0.2334276339508976,
      "ic_60d": NaN,
      "stability_score": 0.6631524530448877
    },
    {
      "feature": "ma_10",
      "missing_rate": 0.0,
      "drift_score": 0.1017169758953196,
      "ic_20d": -0.22986444155717073,
      "ic_60d": NaN,
      "stability_score": 0.6625285169254814
    },
    {
      "feature": "ema_12",
      "missing_rate": 0.0,
      "drift_score": 0.10170923399950094,
      "ic_20d": -0.22927096951440123,
      "ic_60d": NaN,
      "stability_score": 0.6624265728315678
    },
    {
      "feature": "High",
      "missing_rate": 0.0,
      "drift_score": 0.10170376085869622,
      "ic_20d": -0.2262824966060701,
      "ic_60d": NaN,
      "stability_score": 0.6619049428491229
    },
    {
      "feature": "ma_5",
      "missing_rate": 0.0,
      "drift_score": 0.10170096472247767,
      "ic_20d": -0.22434770063174317,
      "ic_60d": NaN,
      "stability_score": 0.661567044669728
    },
    {
      "feature": "bb_lower",
      "missing_rate": 0.0,
      "drift_score": 0.10170939109993812,
      "ic_20d": -0.22427226683294732,
      "ic_60d": NaN,
      "stability_score": 0.6615517610325622
    },
    {
      "feature": "Open",
      "missing_rate": 0.0,
      "drift_score": 0.10170045748857763,
      "ic_20d": -0.22365689654743995,
      "ic_60d": NaN,
      "stability_score": 0.6614462793274692
    },
    {
      "feature": "Close",
      "missing_rate": 0.0,
      "drift_score": 0.10169609166882196,
      "ic_20d": -0.22344799695880027,
      "ic_60d": NaN,
      "stability_score": 0.6614108009995205
    },
    {
      "feature": "Low",
      "missing_rate": 0.0,
      "drift_score": 0.10169031920826528,
      "ic_20d": -0.22053594038135854,
      "ic_60d": NaN,
      "stability_score": 0.660902617891195
    }
  ],
  "top_unstable_features": [
    {
      "feature": "ma_250",
      "missing_rate": 1.0,
      "drift_score": 0.0,
      "ic_20d": NaN,
      "ic_60d": NaN,
      "stability_score": 0.3
    },
    {
      "feature": "volume_change",
      "missing_rate": 0.00033944331296673454,
      "drift_score": Infinity,
      "ic_20d": 0.03127739696539096,
      "ic_60d": NaN,
      "stability_score": 0.35535473930940503
    },
    {
      "feature": "blue_weekly",
      "missing_rate": 0.0,
      "drift_score": 0.4219166559957321,
      "ic_20d": -0.028988545288443614,
      "ic_60d": NaN,
      "stability_score": 0.5660558253508488
    },
    {
      "feature": "fund_has_market_cap",
      "missing_rate": 0.0,
      "drift_score": 0.3574953375829947,
      "ic_20d": -0.08656351246851021,
      "ic_60d": NaN,
      "stability_score": 0.586143848841796
    },
    {
      "feature": "fund_cap_mid",
      "missing_rate": 0.0,
      "drift_score": 0.2677351647865707,
      "ic_20d": -0.004952363444277257,
      "ic_60d": NaN,
      "stability_score": 0.5875091488259981
    },
    {
      "feature": "fund_market_cap_log",
      "missing_rate": 0.0,
      "drift_score": 0.3613422994323923,
      "ic_20d": -0.1370914913267258,
      "ic_60d": NaN,
      "stability_score": 0.594361743695826
    },
    {
      "feature": "momentum_60",
      "missing_rate": 0.0006788866259334691,
      "drift_score": 0.36745608451443007,
      "ic_20d": 0.1589834090466559,
      "ic_60d": NaN,
      "stability_score": 0.5969699593314203
    },
    {
      "feature": "return_60d",
      "missing_rate": 0.0006788866259334691,
      "drift_score": 0.3674560845144296,
      "ic_20d": 0.1589834090466559,
      "ic_60d": NaN,
      "stability_score": 0.5969699593314203
    },
    {
      "feature": "blue_monthly",
      "missing_rate": 0.0,
      "drift_score": 0.24385098010181452,
      "ic_20d": 0.048928280953852626,
      "ic_60d": NaN,
      "stability_score": 0.5997488973823235
    },
    {
      "feature": "rsi_oversold",
      "missing_rate": 0.0,
      "drift_score": 0.20974542484649084,
      "ic_20d": 0.011843148780742234,
      "ic_60d": NaN,
      "stability_score": 0.6000586097878486
    },
    {
      "feature": "near_high_20",
      "missing_rate": 0.0,
      "drift_score": 0.1997547100680954,
      "ic_20d": 0.028889014932151923,
      "ic_60d": NaN,
      "stability_score": 0.6051066901300949
    },
    {
      "feature": "obv_ma",
      "missing_rate": 0.0,
      "drift_score": 0.18877549068846505,
      "ic_20d": -0.024350855724227037,
      "ic_60d": NaN,
      "stability_score": 0.6066219189160931
    },
    {
      "feature": "rsi_14",
      "missing_rate": 0.0,
      "drift_score": 0.21346204474983838,
      "ic_20d": -0.056742833739783456,
      "ic_60d": NaN,
      "stability_score": 0.6071565171607133
    },
    {
      "feature": "kdj_d",
      "missing_rate": 0.0,
      "drift_score": 0.20251146221425523,
      "ic_20d": -0.04968267726201748,
      "ic_60d": NaN,
      "stability_score": 0.6081723399812983
    },
    {
      "feature": "near_high_60",
      "missing_rate": 0.0,
      "drift_score": 0.17046943731891961,
      "ic_20d": 0.021730200111610556,
      "ic_60d": NaN,
      "stability_score": 0.6101102035944078
    },
    {
      "feature": "ma_60_bias",
      "missing_rate": 0.0005091649694501018,
      "drift_score": 0.2766204087482886,
      "ic_20d": 0.14955062136494507,
      "ic_60d": NaN,
      "stability_score": 0.610988610843527
    },
    {
      "feature": "obv",
      "missing_rate": 0.0,
      "drift_score": 0.18715878392433827,
      "ic_20d": -0.051541357238028614,
      "ic_60d": NaN,
      "stability_score": 0.611723928449146
    },
    {
      "feature": "roc_20",
      "missing_rate": 0.0,
      "drift_score": 0.17512989060146444,
      "ic_20d": 0.13113232879712725,
      "ic_60d": NaN,
      "stability_score": 0.6282390852908556
    },
    {
      "feature": "momentum_20",
      "missing_rate": 0.0,
      "drift_score": 0.17512989060146403,
      "ic_20d": 0.13113232879712725,
      "ic_60d": NaN,
      "stability_score": 0.6282390852908556
    },
    {
      "feature": "return_20d",
      "missing_rate": 0.0,
      "drift_score": 0.17512989060146433,
      "ic_20d": 0.13113232879712725,
      "ic_60d": NaN,
      "stability_score": 0.6282390852908556
    },
    {
      "feature": "fund_industry_hash",
      "missing_rate": 0.0,
      "drift_score": 0.10668307378255337,
      "ic_20d": -0.05692580367803489,
      "ic_60d": NaN,
      "stability_score": 0.6310423340356454
    },
    {
      "feature": "kdj_k",
      "missing_rate": 0.0,
      "drift_score": 0.1019077824755319,
      "ic_20d": -0.058558037412070996,
      "ic_60d": NaN,
      "stability_score": 0.6325027442877796
    },
    {
      "feature": "rsi_overbought",
      "missing_rate": 0.0,
      "drift_score": 0.07544294620359909,
      "ic_20d": 0.021730200111610556,
      "ic_60d": NaN,
      "stability_score": 0.6327576110835497
    },
    {
      "feature": "macd_hist_trend",
      "missing_rate": 0.0,
      "drift_score": 0.08881238424202322,
      "ic_20d": 0.06004676802260571,
      "ic_60d": NaN,
      "stability_score": 0.6360377470189559
    },
    {
      "feature": "ma_10_20_cross",
      "missing_rate": 0.0,
      "drift_score": 0.08433208454593168,
      "ic_20d": 0.05579794562955695,
      "ic_60d": NaN,
      "stability_score": 0.6364326504755123
    },
    {
      "feature": "kdj_oversold",
      "missing_rate": 0.0,
      "drift_score": 0.052500586406188446,
      "ic_20d": 0.010199103683248863,
      "ic_60d": NaN,
      "stability_score": 0.6368203137891634
    },
    {
      "feature": "volume_shrink",
      "missing_rate": 0.0,
      "drift_score": 0.12166216412075571,
      "ic_20d": 0.11528867758776751,
      "ic_60d": NaN,
      "stability_score": 0.6376357303923166
    },
    {
      "feature": "ma_bullish",
      "missing_rate": 0.0,
      "drift_score": 0.04120428217151646,
      "ic_20d": NaN,
      "ic_60d": NaN,
      "stability_score": 0.638127896837233
    },
    {
      "feature": "volume_surge",
      "missing_rate": 0.0,
      "drift_score": 0.055721494690491515,
      "ic_20d": 0.02633255276551526,
      "ic_60d": NaN,
      "stability_score": 0.6387740506156764
    },
    {
      "feature": "ma_120",
      "missing_rate": 0.0855397148676171,
      "drift_score": 0.1077255000742526,
      "ic_20d": -0.28186109061022796,
      "ic_60d": NaN,
      "stability_score": 0.6402120086154173
    }
  ]
}